connection/__init__.py
connection/api.py
connection/file.py
connection/mongodb.py
connection/mysql.py
connection/postgresql.py
integration/__init__.py
integration/clean.py
integration/transform.py
metadata/__init__.py
metadata/credential.py
metadata/input.py
metadata/quality.py
quality/__init__.py
quality/quality.py
quality/test_quality.py
test/__init__.py
test/test_fungsi.py
sagala_framework-0.1.3.dist-info/LICENSE.txt
sagala_framework-0.1.3.dist-info/METADATA
sagala_framework-0.1.3.dist-info/WHEEL
sagala_framework-0.1.3.dist-info/top_level.txt
sagala_framework-0.1.3.dist-info/RECORD
