Metadata-Version: 2.1
Name: sagala-framework
Version: 0.1.3
Summary: Test buat library python
Home-page: UNKNOWN
Author: riskaamalia
Author-email: UNKNOWN
License: MIT
Platform: UNKNOWN
Requires-Dist: pandas
